vivify/__init__.py
vivify/vivify.py
vivify-1.0.1.dist-info/LICENSE.txt
vivify-1.0.1.dist-info/WHEEL
vivify-1.0.1.dist-info/METADATA
vivify-1.0.1.dist-info/RECORD
