Metadata-Version: 2.1
Name: vivify
Version: 1.0.1
Summary: A Python library for using INI files to instantiate classes.
Home-page: https://github.com/wlkr/vivify
License: Apache-2.0
Author: Adam David Walker
Author-email: adam@wlkr.dev
Maintainer: Adam David Walker
Maintainer-email: adam@wlkr.dev
Requires-Python: >=3.9,<4.0
Classifier: License :: OSI Approved :: Apache Software License
Classifier: Programming Language :: Python :: 3
Classifier: Programming Language :: Python :: 3.10
Classifier: Programming Language :: Python :: 3.9
Requires-Dist: typing-inspect (>=0.7.1,<0.8.0)
Project-URL: Documentation, https://github.com/wlkr/vivify
Project-URL: Repository, https://github.com/wlkr/vivify
